LICENSE
README.md
setup.py
kaldiliau.egg-info/PKG-INFO
kaldiliau.egg-info/SOURCES.txt
kaldiliau.egg-info/dependency_links.txt
kaldiliau.egg-info/requires.txt
kaldiliau.egg-info/top_level.txt
tsuan/kaldiliau/__init__.py
tsuan/kaldiliau/kesi.py
tsuan/kaldiliau/piansik_liansuann.py
tsuan/kaldiliau/poo_lomaji_liansuann.py
tsuan/kaldiliau/poo_tuisiau_liansuann.py
tsuan/kaldiliau/suansu_liansuann.py
tsuan/kaldiliau/vad_liansuann.py