Metadata-Version: 2.1
Name: kaldiliau
Version: 0.2.0
Summary: Kaldi ê liāu.
Home-page: https://ithuan.tw
Author: ÌTHUÂNKHOKI
Author-email: ithuan@ithuan.tw
Keywords: Gí-im Piān-sik
Classifier: Development Status :: 3 - Alpha
Classifier: Operating System :: Unix
Classifier: Programming Language :: Python :: 3.7
Classifier: Programming Language :: Python :: 3.8
License-File: LICENSE
